aws_flask_lambda_swagger_ui/aws_flask_lambda_swagger_ui.py
aws_flask_lambda_swagger_ui-0.1.3.dist-info/METADATA
aws_flask_lambda_swagger_ui-0.1.3.dist-info/WHEEL
aws_flask_lambda_swagger_ui-0.1.3.dist-info/top_level.txt
aws_flask_lambda_swagger_ui-0.1.3.dist-info/RECORD
