Metadata-Version: 2.1
Name: aws-flask-lambda-swagger-ui
Version: 0.1.3
Summary: Adding swagger ui on your AWS Lambda Function using a Flask blueprint
Home-page: UNKNOWN
Author: Seven Clouds Technologies
Author-email: admin@seventechnologies.cloud
License: UNKNOWN
Platform: UNKNOWN
Classifier: Programming Language :: Python :: 3.8
Classifier: License :: OSI Approved :: MIT License
Classifier: Operating System :: OS Independent
Requires-Dist: Flask (==2.0.2)
